cloudwatchlogs_s3_stream_descriptor/__init__.py
cloudwatchlogs_s3_stream_descriptor/cloud_watch_and_s3_parent.py
cloudwatchlogs_s3_stream_descriptor/cloud_watch_s3_logs_context.py
cloudwatchlogs_s3_stream_descriptor/cloud_watch_s3_stream.py
cloudwatchlogs_s3_stream_descriptor/cloud_watch_s3_subprocess.py
cloudwatchlogs_s3_stream_descriptor/env_config_loader.py
cloudwatchlogs_s3_stream_descriptor/cloud_watch/__init__.py
cloudwatchlogs_s3_stream_descriptor/cloud_watch/cloud_watch_logs_logger.py
cloudwatchlogs_s3_stream_descriptor/cloud_watch/cloud_watch_logs_stream.py
cloudwatchlogs_s3_stream_descriptor/cloud_watch/cloud_watch_parent.py
cloudwatchlogs_s3_stream_descriptor/cloud_watch/standerd_stream_cloud_watch_logs_sender.py
cloudwatchlogs_s3_stream_descriptor/s3/__init__.py
cloudwatchlogs_s3_stream_descriptor/s3/s3_log_context.py
cloudwatchlogs_s3_stream_descriptor/s3/s3_parent.py
cloudwatchlogs_s3_stream_descriptor/s3/s3_stream.py
cloudwatchlogs_s3_stream_descriptor/s3/standerd_stream_s3_sender.py
cloudwatchlogs_s3_stream_descriptor-0.1.0.dist-info/licenses/LICENSE
cloudwatchlogs_s3_stream_descriptor-0.1.0.dist-info/METADATA
cloudwatchlogs_s3_stream_descriptor-0.1.0.dist-info/WHEEL
cloudwatchlogs_s3_stream_descriptor-0.1.0.dist-info/top_level.txt
cloudwatchlogs_s3_stream_descriptor-0.1.0.dist-info/RECORD
