Metadata-Version: 2.4
Name: cloudwatchlogs-s3-stream-descriptor
Version: 0.1.0
Summary: AWS CloudWatch LogsとS3へのストリーム出力を行うPythonライブラリ
Home-page: https://github.com/h10x64/CloudWatchLogs-S3-Stream-Descriptor
Author: n_h
Author-email: h.10x64@gmail.com
Keywords: aws cloudwatch logs s3 stream logging
Classifier: Development Status :: 3 - Alpha
Classifier: Intended Audience :: Developers
Classifier: License :: CC0 1.0 Universal (CC0 1.0) Public Domain Dedication
Classifier: Programming Language :: Python :: 3
Classifier: Programming Language :: Python :: 3.7
Classifier: Programming Language :: Python :: 3.8
Classifier: Programming Language :: Python :: 3.9
Classifier: Programming Language :: Python :: 3.10
Classifier: Programming Language :: Python :: 3.11
Classifier: Topic :: System :: Logging
Classifier: Topic :: Software Development :: Libraries :: Python Modules
Requires-Python: >=3.7
License-File: LICENSE
Requires-Dist: boto3>=1.26.0
Requires-Dist: python-dotenv>=0.19.0
Dynamic: author
Dynamic: author-email
Dynamic: classifier
Dynamic: description
Dynamic: description-content-type
Dynamic: home-page
Dynamic: keywords
Dynamic: license-file
Dynamic: requires-dist
Dynamic: requires-python
Dynamic: summary
